{
  "Name": "vtexid_configure_active_password",
  "FriendlyName": "[VTEXID] Registration Confirmation",
  "Description": "E-mail sent when registration is confirmed.",
  "IsDefaultTemplate": true,
  "AccountId": "2e7a7b8b-f824-4cac-baf3-95e0a38fdf70",
  "AccountName": "storebaseeses",
  "ApplicationId": 22,
  "IsPersisted": true,
  "IsRemoved": false,
  "Type": "",
  "Templates": {
    "email": {
      "To": "{{#each to}}{{email}},{{/each}}",
      "CC": "{{#each cc}}{{email}},{{/each}}",
      "BCC": null,
      "Subject": "Confirmação de cadastro",
      "Message": "vtexid_configure_active_password.html",
      "Type": "E",
      "ProviderId": "00000000-0000-0000-0000-000000000000",
      "ProviderName": null,
      "IsActive": true,
      "withError": false
    },
    "sms": {
      "Type": "S",
      "ProviderId": "00000000-0000-0000-0000-000000000000",
      "ProviderName": null,
      "IsActive": false,
      "withError": false,
      "Parameters": []
    }
  }
}